decoratedtext/__init__.py
decoratedtext/main.py
decoratedtext-1.0.dist-info/METADATA
decoratedtext-1.0.dist-info/WHEEL
decoratedtext-1.0.dist-info/licenses/LICENSE
decoratedtext-1.0.dist-info/RECORD
