Metadata-Version: 2.4
Name: DecoratedText
Version: 1.0
Summary: It's a great library for text design!
License-File: LICENSE
Classifier: License :: OSI Approved :: MIT License
Classifier: Operating System :: OS Independent
Classifier: Programming Language :: Python :: 3
Requires-Python: >=3.5.0
